mkdocs_image_gallery_plugin/__init__.py
mkdocs_image_gallery_plugin/plugin.py
mkdocs_image_gallery_plugin/youtube.py
mkdocs_image_gallery_plugin/assets/css/styles.css
mkdocs_image_gallery_plugin/assets/js/youtube-gallery.js
mkdocs_image_gallery_plugin/assets/templates/youtube_gallery.html
mkdocs_image_gallery_plugin-1.3.0.data/data/styles.css
mkdocs_image_gallery_plugin-1.3.0.dist-info/licenses/LICENSE
mkdocs_image_gallery_plugin-1.3.0.dist-info/METADATA
mkdocs_image_gallery_plugin-1.3.0.dist-info/WHEEL
mkdocs_image_gallery_plugin-1.3.0.dist-info/entry_points.txt
mkdocs_image_gallery_plugin-1.3.0.dist-info/top_level.txt
mkdocs_image_gallery_plugin-1.3.0.dist-info/RECORD
