Metadata-Version: 2.4
Name: mkdocs-image-gallery-plugin
Version: 1.3.0
Summary: An MkDocs plugin to generate an image gallery from a folder of images
Author: APinchofDill
License-Expression: MIT
Project-URL: Homepage, https://github.com/APinchofDill/mkdocs-image-gallery-plugin
Keywords: mkdocs,image,gallery
Classifier: Programming Language :: Python :: 3
Classifier: Operating System :: OS Independent
Requires-Python: >=3.8
License-File: LICENSE
Requires-Dist: jinja2>=3.1.4
Requires-Dist: mkdocs>=1.4.1
Requires-Dist: PyYAML>=6.0.1
Dynamic: license-file
